spot_nmf-0.1.0.dist-info/licenses/LICENSE
spotnmf/__init__.py
spotnmf/_version.py
spotnmf/annotate.py
spotnmf/cli.py
spotnmf/enrichment.py
spotnmf/eval.py
spotnmf/gscore.py
spotnmf/hvg.py
spotnmf/io.py
spotnmf/models.py
spotnmf/niche_networks.py
spotnmf/pl.py
spotnmf/utils.py
spot_nmf-0.1.0.dist-info/METADATA
spot_nmf-0.1.0.dist-info/WHEEL
spot_nmf-0.1.0.dist-info/entry_points.txt
spot_nmf-0.1.0.dist-info/top_level.txt
spot_nmf-0.1.0.dist-info/RECORD
