Metadata-Version: 2.4
Name: spot-nmf
Version: 0.1.0
Summary: Optimal Transport-based Matrix Factorization for spatial transcriptomics deconvolution.
Home-page: https://github.com/MorrissyLab/spOT-NMF
Author: Aly O. Abdelkareem, Morrissy Lab
License:                     GNU GENERAL PUBLIC LICENSE
Project-URL: Homepage, https://github.com/MorrissyLab/spOT-NMF
Project-URL: Issues, https://github.com/MorrissyLab/spOT-NMF/issues
Project-URL: Source, https://github.com/MorrissyLab/spOT-NMF
Keywords: spatial transcriptomics,single-cell,omics,optimal transport,NMF
Classifier: Development Status :: 3 - Alpha
Classifier: Intended Audience :: Science/Research
Classifier: License :: OSI Approved :: GNU General Public License v3 (GPLv3)
Classifier: Programming Language :: Python :: 3
Classifier: Programming Language :: Python :: 3 :: Only
Classifier: Topic :: Scientific/Engineering :: Bio-Informatics
Requires-Python: >=3.8
License-File: LICENSE
Requires-Dist: numpy==1.26.4
Requires-Dist: scipy==1.16.2
Requires-Dist: pandas==2.3.3
Requires-Dist: scikit-learn==1.7.2
Requires-Dist: matplotlib<3.11,>=3.7
Requires-Dist: seaborn>=0.12
Requires-Dist: anndata==0.9.2
Requires-Dist: scanpy==1.9.3
Requires-Dist: igraph>=0.10
Requires-Dist: leidenalg>=0.10
Requires-Dist: networkx>=3.1
Requires-Dist: umap-learn>=0.5.4
Requires-Dist: pynndescent>=0.5
Requires-Dist: statsmodels>=0.14
Requires-Dist: pygam>=0.9
Requires-Dist: natsort>=8.4
Requires-Dist: tqdm>=4.65
Requires-Dist: progressbar2>=4.4
Requires-Dist: session-info>=1.0
Requires-Dist: distinctipy>=1.3.4
Requires-Dist: rbo==0.1.3
Requires-Dist: fastcluster==1.2.6
Requires-Dist: adjustText>=0.8
Requires-Dist: texttable>=1.7
Requires-Dist: requests>=2.31
Requires-Dist: charset-normalizer>=3.3
Requires-Dist: idna>=3.4
Requires-Dist: urllib3>=2.0
Requires-Dist: gprofiler-official==1.0.0
Provides-Extra: dev
Requires-Dist: pytest>=7.4; extra == "dev"
Provides-Extra: docs
Requires-Dist: mkdocs>=1.5; extra == "docs"
Requires-Dist: mkdocs-material>=9.5; extra == "docs"
Requires-Dist: mkdocstrings[python]>=0.24; extra == "docs"
Provides-Extra: torch
Requires-Dist: torch; extra == "torch"
Requires-Dist: torchvision; extra == "torch"
Requires-Dist: torchaudio; extra == "torch"
Dynamic: home-page
Dynamic: license-file
Dynamic: requires-python
